nonebot_plugin_comment_analysis/SourceHanSans.otf
nonebot_plugin_comment_analysis/__init__.py
nonebot_plugin_comment_analysis/ai_summary.py
nonebot_plugin_comment_analysis/bilibili_analysis.py
nonebot_plugin_comment_analysis/config.py
nonebot_plugin_comment_analysis-0.2.3.dist-info/licenses/LICENSE
nonebot_plugin_comment_analysis-0.2.3.dist-info/METADATA
nonebot_plugin_comment_analysis-0.2.3.dist-info/WHEEL
nonebot_plugin_comment_analysis-0.2.3.dist-info/top_level.txt
nonebot_plugin_comment_analysis-0.2.3.dist-info/RECORD
