Metadata-Version: 2.4
Name: nonebot-plugin-comment-analysis
Version: 0.2.3
Summary: NoneBot2 插件：解析 B 站链接并生成评论、弹幕与 AI 分析
Author-email: lbsucceed <woaikanpika123@gmail.com>
License: The MIT License (MIT)
Project-URL: Repository, https://github.com/lbsucceed/nonebot-plugin-comment-analysis
Project-URL: Issues, https://github.com/lbsucceed/nonebot-plugin-comment-analysis/issues
Keywords: nonebot,bilibili,analysis,wordcloud,plugin
Classifier: Development Status :: 3 - Alpha
Classifier: Framework :: AsyncIO
Classifier: Intended Audience :: Developers
Classifier: License :: OSI Approved :: MIT License
Classifier: Programming Language :: Python :: 3
Classifier: Programming Language :: Python :: 3 :: Only
Classifier: Topic :: Internet
Classifier: Topic :: Software Development :: Libraries :: Application Frameworks
Requires-Python: >=3.9
License-File: LICENSE
Requires-Dist: nonebot2>=2.2.0
Requires-Dist: nonebot-adapter-onebot>=2.4.4
Requires-Dist: aiofiles>=23.1.0
Requires-Dist: httpx>=0.25.2
Requires-Dist: bilibili-api-python>=16.2.0
Requires-Dist: beautifulsoup4>=4.12.0
Requires-Dist: colorama>=0.4.6
Requires-Dist: lxml>=4.9.0
Requires-Dist: PyYAML>=6.0
Requires-Dist: brotli>=1.0.9
Requires-Dist: qrcode>=7.4.0
Requires-Dist: qrcode-terminal>=0.8
Requires-Dist: APScheduler>=3.10
Requires-Dist: PyJWT>=2.8
Requires-Dist: yarl>=1.9.4
Requires-Dist: pycryptodomex>=3.20.0
Requires-Dist: wordcloud>=1.9.3
Requires-Dist: jieba>=0.42.1
Requires-Dist: numpy>=1.23.0
Requires-Dist: Pillow>=9.5.0
Requires-Dist: emoji>=2.8.0
Dynamic: license-file
